pyfernsehserien/__init__.py
pyfernsehserien/exceptions.py
pyfernsehserien/fernsehserien.py
pyfernsehserien/parser.py
pyfernsehserien/session.py
pyfernsehserien/utils.py
pyfernsehserien-1.0.0.dist-info/LICENSE
pyfernsehserien-1.0.0.dist-info/METADATA
pyfernsehserien-1.0.0.dist-info/WHEEL
pyfernsehserien-1.0.0.dist-info/RECORD
