Metadata-Version: 2.1
Name: pyfernsehserien
Version: 1.0.0
Summary: A scraper for fernsehserien.de
Home-page: https://github.com/u2ly/pyfernsehserien
License: GPL-3.0-only
Keywords: fernsehserien,scraper,python
Author: u2ly
Author-email: 76696f6c@proton.me
Requires-Python: >=3.9,<4.0
Classifier: License :: OSI Approved :: GNU General Public License v3 (GPLv3)
Classifier: Programming Language :: Python :: 3
Classifier: Programming Language :: Python :: 3.9
Classifier: Programming Language :: Python :: 3.10
Classifier: Programming Language :: Python :: 3.11
Classifier: Programming Language :: Python :: 3.12
Requires-Dist: beautifulsoup4 (>=4.12.3,<5.0.0)
Requires-Dist: requests (>=2.31.0,<3.0.0)
Project-URL: Repository, https://github.com/u2ly/pyfernsehserien
